minumtium_simple_jwt_auth/__init__.py
minumtium_simple_jwt_auth-1.1.0.dist-info/LICENSE
minumtium_simple_jwt_auth-1.1.0.dist-info/METADATA
minumtium_simple_jwt_auth-1.1.0.dist-info/WHEEL
minumtium_simple_jwt_auth-1.1.0.dist-info/top_level.txt
minumtium_simple_jwt_auth-1.1.0.dist-info/RECORD
