Metadata-Version: 2.1
Name: minumtium-simple-jwt-auth
Version: 1.1.0
Summary: A JWT token adapter for the minumtium library.
Home-page: https://github.com/danodic-dev/minumtium-simple-jwt-auth
Author: Danilo Guimaraes (danodic)
Author-email: danilo@danodic.dev
Project-URL: Bug Tracker, https://github.com/danodic-dev/minumtium-simple-jwt-auth/issues
Classifier: Development Status :: 3 - Alpha
Classifier: Programming Language :: Python :: 3
Classifier: License :: OSI Approved :: Apache Software License
Classifier: Operating System :: OS Independent
Requires-Python: >=3.6
License-File: LICENSE
Requires-Dist: bcrypt
Requires-Dist: pyjwt
Requires-Dist: minumtium
